LICENSE
MANIFEST.in
README.md
requirements.txt
setup.cfg
setup.py
comments/__init__.py
comments/admin.py
comments/forms.py
comments/models.py
comments/urls.py
comments/views.py
comments/locale/en/LC_MESSAGES/django.mo
comments/locale/en/LC_MESSAGES/django.po
comments/locale/ru/LC_MESSAGES/django.mo
comments/locale/ru/LC_MESSAGES/django.po
comments/locale/uk/LC_MESSAGES/django.mo
comments/locale/uk/LC_MESSAGES/django.po
comments/migrations/0001_initial.py
comments/migrations/__init__.py
comments/static/comments/comments.js
comments/templates/comments/form.html
comments/templates/comments/index.html
comments/templates/comments/list_item.html
comments/templatetags/__init__.py
comments/templatetags/comments.py
django_mp_comments.egg-info/PKG-INFO
django_mp_comments.egg-info/SOURCES.txt
django_mp_comments.egg-info/dependency_links.txt
django_mp_comments.egg-info/requires.txt
django_mp_comments.egg-info/top_level.txt