Metadata-Version: 1.1
Name: django-mp-comments
Version: 1.0
Summary: Django comments apps
Home-page: https://github.com/pmaigutyak/mp-comments
Author: Paul Maigutyak
Author-email: pmaigutyak@gmail.com
License: MIT
Download-URL: https://github.com/pmaigutyak/mp-comments/archive/1.0.tar.gz
Platform: UNKNOWN
